pytestify/__init__.py
pytestify/__main__.py
pytestify/_ast_helpers.py
pytestify/_main.py
pytestify/_token_helpers.py
pytestify/fixes/__init__.py
pytestify/fixes/asserts.py
pytestify/fixes/base_class.py
pytestify/fixes/funcs.py
pytestify/fixes/imports.py
pytestify/fixes/method_name.py
pytestify-1.5.0.dist-info/LICENSE
pytestify-1.5.0.dist-info/METADATA
pytestify-1.5.0.dist-info/WHEEL
pytestify-1.5.0.dist-info/entry_points.txt
pytestify-1.5.0.dist-info/top_level.txt
pytestify-1.5.0.dist-info/RECORD
