Metadata-Version: 2.1
Name: pytestify
Version: 1.5.0
Summary: Automatically convert unittests to pytest
Home-page: https://github.com/dannysepler/pytestify
Author: Danny Sepler
Author-email: dannysepler@gmail.com
License: MIT
Project-URL: Bug Tracker, https://github.com/dannysepler/pytestify/issues
Classifier: License :: OSI Approved :: MIT License
Classifier: Programming Language :: Python :: 3
Classifier: Programming Language :: Python :: 3 :: Only
Requires-Python: >=3.7
License-File: LICENSE
Requires-Dist: tokenize-rt (>=4.0.0)
